cantal_tools/__init__.py
cantal_tools/_fork.py
cantal_tools/django.py
cantal_tools/elasticsearch.py
cantal_tools/flask.py
cantal_tools/metrics.py
cantal_tools/redis.py
cantal_tools/sqlalchemy.py
cantal_tools/werkzeug_serving.py
cantal_tools-0.2.4.dist-info/DESCRIPTION.rst
cantal_tools-0.2.4.dist-info/METADATA
cantal_tools-0.2.4.dist-info/RECORD
cantal_tools-0.2.4.dist-info/WHEEL
cantal_tools-0.2.4.dist-info/metadata.json
cantal_tools-0.2.4.dist-info/top_level.txt
