Metadata-Version: 2.0
Name: cantal-tools
Version: 0.2.4
Summary: High level cantal tools
Home-page: https://github.com/popravich/cantal_tools
Author: Alexey Popravka
Author-email: alexey.popravka@horsedevel.com
License: MIT
Platform: POSIX
Classifier: Development Status :: 4 - Beta
Classifier: Intended Audience :: Developers
Classifier: License :: OSI Approved :: MIT License
Classifier: Operating System :: POSIX :: Linux
Classifier: Programming Language :: Python
Classifier: Programming Language :: Python :: 2
Classifier: Programming Language :: Python :: 3
Classifier: Topic :: Software Development :: Libraries
Requires-Dist: cantal
